.DS_Store
swepy/__init__.py
swepy/swepy.py
swepy/analysis/__init__.py
swepy/analysis/analysis.py
swepy/ease2Transform/__init__.py
swepy/ease2Transform/ease2Transform.py
swepy/nsidcDownloader/__init__.py
swepy/nsidcDownloader/nsidcDownloader.py
swepy/process/__init__.py
swepy/process/process.py
swepy/tests/__init__.py
swepy/tests/mock_server.py
swepy/tests/test_analysis.py
swepy/tests/test_downloader.py
swepy/tests/test_ease.py
swepy/tests/test_login.py
swepy/tests/test_process.py
swepy/tests/test_swepy.py
swepy-1.3.0.dist-info/METADATA
swepy-1.3.0.dist-info/RECORD
swepy-1.3.0.dist-info/WHEEL
swepy-1.3.0.dist-info/top_level.txt
