Metadata-Version: 2.1
Name: swepy
Version: 1.3.0
Summary: A python package for obtaining and manipulating Tb files from the MEaSUREs database
Home-page: https://github.com/wino6687/SWEpy
Author: William Norris
Author-email: wino6687@colorado.edu
License: UNKNOWN
Platform: UNKNOWN
Classifier: Programming Language :: Python :: 3
Classifier: Operating System :: OS Independent
Classifier: License :: OSI Approved :: GNU Lesser General Public License v3 (LGPLv3)
